smart_fetch/__init__.py
smart_fetch/bulk_utils.py
smart_fetch/cli_utils.py
smart_fetch/crawl_utils.py
smart_fetch/filtering.py
smart_fetch/hydrate_utils.py
smart_fetch/iter_utils.py
smart_fetch/lifecycle.py
smart_fetch/merges.py
smart_fetch/ndjson.py
smart_fetch/resources.py
smart_fetch/symlinks.py
smart_fetch/timing.py
smart_fetch/cli/__init__.py
smart_fetch/cli/bulk.py
smart_fetch/cli/bundle.py
smart_fetch/cli/crawl.py
smart_fetch/cli/export.py
smart_fetch/cli/hydrate.py
smart_fetch/cli/main.py
smart_fetch/cli/reset_symlinks.py
smart_fetch/cli/single.py
smart_fetch/tasks/__init__.py
smart_fetch/tasks/inline.py
smart_fetch/tasks/loc.py
smart_fetch/tasks/meds.py
smart_fetch/tasks/obs.py
smart_fetch/tasks/org.py
smart_fetch/tasks/pract.py
smart_fetch-0.6.5.dist-info/entry_points.txt
smart_fetch-0.6.5.dist-info/licenses/LICENSE
smart_fetch-0.6.5.dist-info/WHEEL
smart_fetch-0.6.5.dist-info/METADATA
smart_fetch-0.6.5.dist-info/RECORD
