Metadata-Version: 2.4
Name: smart-fetch
Version: 0.6.5
Summary: Fetch FHIR data from your EHR easily and completely
Author-email: Michael Terry <michael.terry@childrens.harvard.edu>
Requires-Python: >= 3.11
License-Expression: Apache-2.0
Classifier: Operating System :: OS Independent
Classifier: Programming Language :: Python :: 3
Classifier: Topic :: Software Development :: Libraries :: Python Modules
License-File: LICENSE
Requires-Dist: cumulus-fhir-support >= 1.10
Requires-Dist: rich
Requires-Dist: pre-commit ; extra == "dev"
Requires-Dist: ruff < 0.15 ; extra == "dev"
Requires-Dist: ddt ; extra == "tests"
Requires-Dist: httpx ; extra == "tests"
Requires-Dist: pytest ; extra == "tests"
Requires-Dist: pytest-cov ; extra == "tests"
Requires-Dist: respx ; extra == "tests"
Requires-Dist: time-machine ; extra == "tests"
Project-URL: Homepage, https://github.com/smart-on-fhir/smart-fetch
Provides-Extra: dev
Provides-Extra: tests
